{"success":true,"message":null,"code":null,"params":{"data":{"time":null,"nx":161,"ny":161,"startLon":111.9,"endLon":119.9,"startLat":34.8,"endLat":42.8,"dx":0.05,"dy":0.05,"data":null,"data2":null},"gridData":[],"statDataList":[{"gjzid":"","code":"53575","lon":112.25752,"lat":39.07247,"qy":"yp","glb":"5.416","name":"5.416","val":0,"status":112.219,"val2":112.219,"type":0},{"gjzid":"","code":"53577","lon":112.28746,"lat":39.03062,"qy":"yp","glb":"11.514","name":"11.514","val":0,"status":112.298,"val2":112.298,"type":0},{"gjzid":"","code":"53680","lon":114.43992,"lat":38.40695,"name":"283.017","qy":"sn","glb":"283.017","val":0,"status":114.369,"val2":114.369,"type":0},{"gjzid":"","code":"53696","lon":115.01129,"lat":38.48759,"qy":"sn","glb":"327.49","name":"327.49","val":0,"status":115.011,"val2":115.011,"type":0},{"gjzid":"","code":"54604","lon":115.30807,"lat":38.44274,"qy":"sn","glb":"356.155","name":"356.155","val":0,"status":115.325,"val2":115.325,"type":0},{"gjzid":"","code":"54614","lon":116.0554,"lat":38.45342,"qy":"sn","glb":"425.515","name":"425.515","val":0,"status":116.049,"val2":116.049,"type":0},{"gjzid":"","code":"54620","lon":115.56668,"lat":38.46306,"qy":"sn","glb":"379.704","name":"379.704","val":0,"status":115.567,"val2":115.567,"type":0},{"gjzid":"","code":"54624","lon":117.36296,"lat":38.41226,"qy":"sn","glb":"14.591","name":"14.591","val":0,"status":117.355,"val2":117.355,"type":0},{"gjzid":"","code":"54626","lon":115.77002,"lat":38.44594,"qy":"sn","glb":"400.202","name":"400.202","val":0,"status":115.812,"val2":115.812,"type":0},{"gjzid":"","code":"A2601","lon":117.26038,"lat":38.77156,"qy":"sn","glb":"57.95","name":"57.95","val":0,"status":117.267,"val2":117.267,"type":0},{"gjzid":"","code":"A2603","lon":117.24844,"lat":38.71177,"qy":"sn","glb":"49.888","name":"49.888","val":0,"status":117.248,"val2":117.248,"type":0},{"gjzid":"","code":"A2605","lon":117.671,"lat":38.972,"qy":"sn","glb":"71.05","name":"71.05","val":0,"status":117.654,"val2":117.654,"type":0},{"gjzid":"","code":"A2608","lon":117.28057,"lat":38.79523,"qy":"sn","glb":"62.207","name":"62.207","val":0,"status":117.332,"val2":117.332,"type":0},{"gjzid":"","code":"A2661","lon":117.2651,"lat":38.66758,"qy":"sn","glb":"43.266","name":"43.266","val":0,"status":117.274,"val2":117.274,"type":0},{"gjzid":"","code":"A3101","lon":117.762,"lat":38.969,"qy":"sn","glb":"81.05","name":"81.05","val":0,"status":117.678,"val2":117.678,"type":0},{"gjzid":"","code":"B0351","lon":114.82257,"lat":38.49319,"qy":"sn","glb":"315.504","name":"311.504","val":0,"status":114.754,"val2":114.754,"type":0},{"gjzid":"","code":"B0805","lon":114.27882,"lat":38.36027,"qy":"sn","glb":"266.11","name":"266.11","val":0,"status":114.258,"val2":114.258,"type":0},{"gjzid":"","code":"B1300","lon":114.01907,"lat":38.25251,"qy":"sn","glb":"235.721","name":"235.721","val":0,"status":113.946,"val2":113.946,"type":0},{"gjzid":"","code":"B1283","lon":113.76654,"lat":38.38946,"qy":"yp","glb":"206.947","name":"206.947","val":0,"status":113.711,"val2":113.711,"type":0},{"gjzid":"","code":"B1298","lon":113.83742,"lat":38.36585,"qy":"yp","glb":"214.666","name":"214.666","val":0,"status":113.853,"val2":113.853,"type":0},{"gjzid":"","code":"B1291","lon":113.90797,"lat":38.28802,"qy":"yp","glb":"225.773","name":"225.773","val":0,"status":113.615,"val2":113.615,"type":0},{"gjzid":"","code":"B1354","lon":114.60972,"lat":38.45116,"qy":"sn","glb":"297.333","name":"297.333","val":0,"status":114.559,"val2":114.559,"type":0},{"gjzid":"","code":"B1482","lon":115.46499,"lat":38.44196,"qy":"sn","glb":"368.723","name":"368.723","val":0,"status":115.465,"val2":115.465,"type":0},{"gjzid":"","code":"B1523","lon":115.06755,"lat":38.4747,"qy":"sn","glb":"336.863","name":"336.863","val":0,"status":115.095,"val2":115.095,"type":0},{"gjzid":"","code":"B2322","lon":116.63054,"lat":38.38928,"qy":"sn","glb":"481.552","name":"481.552","val":0,"status":116.631,"val2":116.631,"type":0},{"gjzid":"","code":"B2324","lon":117.12091,"lat":38.34385,"qy":"sn","glb":"523.699","name":"523.699","val":0,"status":117.051,"val2":117.051,"type":0},{"gjzid":"","code":"B2332","lon":116.89765,"lat":38.36458,"qy":"sn","glb":"505.241","name":"505.241","val":0,"status":116.898,"val2":116.898,"type":0},{"gjzid":"","code":"B2337","lon":116.52753,"lat":38.39911,"qy":"sn","glb":"469.405","name":"469.405","val":0,"status":116.553,"val2":116.553,"type":0},{"gjzid":"","code":"B2424","lon":117.74675,"lat":38.28005,"qy":"sn","glb":"576.329","name":"576.329","val":0,"status":117.783,"val2":117.783,"type":0},{"gjzid":"","code":"B2498","lon":117.19576,"lat":38.34389,"qy":"sn","glb":"529.846","name":"529.846","val":0,"status":117.151,"val2":117.151,"type":0},{"gjzid":"","code":"B2502","lon":117.47737,"lat":38.3226,"qy":"sn","glb":"550.362","name":"550.362","val":0,"status":117.483,"val2":117.483,"type":0},{"gjzid":"","code":"B2503","lon":117.31913,"lat":38.48348,"qy":"sn","glb":"23.656","name":"23.656","val":0,"status":117.333,"val2":117.333,"type":0},{"gjzid":"","code":"B2504","lon":117.31738,"lat":38.53863,"qy":"sn","glb":"27.786","name":"27.786","val":0,"status":117.318,"val2":117.318,"type":0},{"gjzid":"","code":"B2534","lon":116.41281,"lat":38.43941,"qy":"sn","glb":"456.788","name":"456.788","val":0,"status":116.497,"val2":116.497,"type":0},{"gjzid":"","code":"B2536","lon":116.23722,"lat":38.45608,"qy":"sn","glb":"442.046","name":"442.046","val":0,"status":116.273,"val2":116.273,"type":0},{"gjzid":"","code":"B2538","lon":116.17178,"lat":38.46148,"qy":"sn","glb":"435.879","name":"435.879","val":0,"status":116.172,"val2":116.172,"type":0},{"gjzid":"","code":"B2541","lon":115.98664,"lat":38.44635,"qy":"sn","glb":"421.588","name":"421.588","val":0,"status":115.969,"val2":115.969,"type":0},{"gjzid":"","code":"B2567","lon":117.36574,"lat":38.3278,"qy":"sn","glb":"542.861","name":"542.861","val":0,"status":117.366,"val2":117.366,"type":0},{"gjzid":"","code":"B5697","lon":112.65627,"lat":38.74663,"qy":"yp","glb":"72.003","name":"72.003","val":0,"status":112.671,"val2":112.671,"type":0},{"gjzid":"","code":"B5698","lon":112.7385,"lat":38.64445,"qy":"yp","glb":"88.466","name":"88.466","val":0,"status":112.709,"val2":112.709,"type":0},{"gjzid":"","code":"B5699","lon":112.68712,"lat":38.69882,"qy":"yp","glb":"79.918","name":"79.918","val":0,"status":112.676,"val2":112.676,"type":0},{"gjzid":"","code":"B5703","lon":112.41804,"lat":38.91834,"qy":"yp","glb":"36.387","name":"36.387","val":0,"status":112.426,"val2":112.426,"type":0},{"gjzid":"","code":"B5728","lon":113.22966,"lat":38.58479,"qy":"yp","glb":"134.968","name":"134.968","val":0,"status":113.23,"val2":113.23,"type":0},{"gjzid":"","code":"B5808","lon":112.83849,"lat":38.59596,"qy":"yp","glb":"98.612","name":"98.612","val":0,"status":112.87,"val2":112.87,"type":0},{"gjzid":"","code":"B5788","lon":112.9915,"lat":38.58821,"qy":"yp","glb":"112.773","name":"112.773","val":0,"status":112.956,"val2":112.956,"type":0},{"gjzid":"","code":"B5807","lon":113.07326,"lat":38.62616,"qy":"yp","glb":"121.206","name":"121.206","val":0,"status":113.016,"val2":113.016,"type":0},{"gjzid":"","code":"B6949","lon":113.47228,"lat":38.43847,"qy":"yp","glb":"177.796","name":"177.796","val":0,"status":113.472,"val2":113.472,"type":0},{"gjzid":"","code":"B8487","lon":113.14526,"lat":38.63819,"qy":"yp","glb":"128.353","name":"128.353","val":0,"status":113.145,"val2":113.145,"type":0},{"gjzid":"53575","code":"B5540","lon":112.219,"lat":39.088,"name":"神池南","url":"","qy":"yp","glb":"0.0", "weather":"","val":0,"status":39.088,"val2":39.088,"type":1},{"gjzid":"53577","lon":112.296,"qy":"yp","glb":"15.931","code":"B5570","lat":39.0,"name":"宁武西","url":"","weather":"","val":0,"status":39.0,"val2":39.0,"type":1},{"gjzid":"53673","qy":"yp","glb":"41.866","code":"B5718","lon":112.469,"lat":38.914,"name":"龙宫","url":"","weather":"","val":0,"status":38.914,"val2":38.914,"type":1},{"gjzid":"53673","qy":"yp","glb":"65.458","code":"B5719","lon":112.624,"lat":38.781,"name":"北大牛","url":"","weather":"","val":0,"status":38.781,"val2":38.781,"type":1},{"gjzid":"53673","qy":"yp","glb":"84.306","code":"B5720","lon":112.703,"lat":38.671,"name":"原平南","url":"","weather":"","val":0,"status":38.671,"val2":38.671,"type":1},{"gjzid":"53676","qy":"yp","glb":"108.443","code":"B5738","lon":112.947,"lat":38.576,"name":"回凤","url":"","weather":"","val":0,"status":38.576,"val2":38.576,"type":1},{"gjzid":"53681","qy":"yp","glb":"131.032","code":"B5739","lon":113.171,"lat":38.626,"name":"东冶","url":"","weather":"","val":0,"status":38.626,"val2":38.626,"type":1},{"gjzid":"53681","qy":"yp","glb":"138.872","code":"B5740","lon":113.257,"lat":38.52,"name":"南湾","url":"","weather":"","val":0,"status":38.52,"val2":38.52,"type":1},{"gjzid":"53685","qy":"yp","glb":"165.042","code":"B6900","lon":113.359,"lat":38.443,"name":"滴流磴","url":"","weather":"","val":0,"status":38.443,"val2":38.443,"type":1},{"gjzid":"53694","qy":"yp","glb":"185.200","code":"HB001","lon":113.545,"lat":38.426,"name":"猴刎","url":"","weather":"","val":0,"status":38.426,"val2":38.426,"type":1},{"gjzid":"53694","qy":"yp","glb":"200.700","code":"HB002","lon":113.709,"lat":38.385,"name":"小觉","url":"","weather":"","val":0,"status":38.385,"val2":38.385,"type":1},{"gjzid":"53694","qy":"yp","glb":"219.300","code":"HB003","lon":113.86,"lat":38.33,"name":"古月","url":"","weather":"","val":0,"status":38.33,"val2":38.33,"type":1},{"gjzid":"53694","qy":"yp","glb":"241.353","code":"HB004","lon":114.087,"lat":38.263,"name":"西柏坡","url":"","weather":"","val":0,"status":38.263,"val2":38.263,"type":1},{"gjzid":"53694","qy":"yp","glb":"256.648","code":"HB005","lon":114.208,"lat":38.329,"name":"三汲","url":"","weather":"","val":0,"status":38.329,"val2":38.329,"type":1},{"gjzid":"53680","qy":"sn","glb":"274.001","code":"HB006","lon":114.345,"lat":38.372,"name":"灵寿","url":"","weather":"","val":0,"status":38.372,"val2":38.372,"type":1},{"gjzid":"53688","qy":"sn","glb":"292.171","code":"HB007","lon":114.535,"lat":38.443,"name":"行唐","url":"","weather":"","val":0,"status":38.443,"val2":38.443,"type":1},{"gjzid":"53696","qy":"sn","glb":"306.355","code":"HB008","lon":114.729,"lat":38.496,"name":"新曲","url":"","weather":"","val":0,"status":38.496,"val2":38.496,"type":1},{"gjzid":"53696","qy":"sn","glb":"319.038","code":"HB009","lon":114.96,"lat":38.488,"name":"定州西","url":"","weather":"","val":0,"status":38.488,"val2":38.488,"type":1},{"gjzid":"53696","qy":"sn","glb":"342.988","code":"HB010","lon":115.105,"lat":38.471,"name":"定州东","url":"","weather":"","val":0,"status":38.471,"val2":38.471,"type":1},{"gjzid":"54604","qy":"sn","glb":"359.888","code":"HB011","lon":115.365,"lat":38.433,"name":"安国","url":"","weather":"","val":0,"status":38.433,"val2":38.433,"type":1},{"gjzid":"54620","qy":"sn","glb":"372.477","code":"HB012","lon":115.508,"lat":38.447,"name":"博野","url":"","weather":"","val":0,"status":38.447,"val2":38.447,"type":1},{"gjzid":"54620","qy":"sn","glb":"383.457","code":"HB013","lon":115.599,"lat":38.466,"name":"蠡县","url":"","weather":"","val":0,"status":38.466,"val2":38.466,"type":1},{"gjzid":"54626","qy":"sn","glb":"406.038","code":"HB014","lon":115.832,"lat":38.443,"name":"肃宁北","url":"","weather":"","val":0,"status":38.443,"val2":38.443,"type":1},{"gjzid":"54626","qy":"sn","glb":"417.388","code":"HB015","lon":115.913,"lat":38.452,"name":"太师庄","url":"","weather":"","val":0,"status":38.452,"val2":38.452,"type":1},{"gjzid":"54614","qy":"sn","glb":"426.477","code":"HB016","lon":116.072,"lat":38.457,"name":"河间","url":"","weather":"","val":0,"status":38.457,"val2":38.457,"type":1},{"gjzid":"54614","qy":"sn","glb":"446.527","code":"HB017","lon":116.285,"lat":38.451,"name":"行别营","url":"","weather":"","val":0,"status":38.451,"val2":38.451,"type":1},{"gjzid":"54614","qy":"sn","glb":"464.028","code":"HB018","lon":116.497,"lat":38.407,"name":"黎民居","url":"","weather":"","val":0,"status":38.407,"val2":38.407,"type":1},{"gjzid":"54616","qy":"sn","glb":"474.648","code":"HB019","lon":116.557,"lat":38.391,"name":"杜生","url":"","weather":"","val":0,"status":38.391,"val2":38.391,"type":1},{"gjzid":"54616","qy":"sn","glb":"495.798","code":"HB020","lon":116.78,"lat":38.373,"name":"沧州西","url":"","weather":"","val":0,"status":38.373,"val2":38.373,"type":1},{"gjzid":"54616","qy":"sn","glb":"515.962","code":"HB021","lon":117.04,"lat":38.326,"name":"李天木","url":"","weather":"","val":0,"status":38.326,"val2":38.326,"type":1},{"gjzid":"54624","qy":"sn","glb":"539.662","code":"HB022","lon":117.318,"lat":38.333,"name":"黄骅南","url":"","weather":"","val":0,"status":38.333,"val2":38.333,"type":1},{"gjzid":"54624","qy":"sn","glb":"559.962","code":"HB023","lon":117.615,"lat":38.288,"name":"段庄","url":"","weather":"","val":0,"status":38.288,"val2":38.288,"type":1},{"gjzid":"54624","qy":"sn","glb":"582.621","code":"HB024","lon":117.797,"lat":38.284,"name":"黄骅港","url":"","weather":"","val":0,"status":38.284,"val2":38.284,"type":1},{"gjzid":"54624","qy":"sn","glb":"9.100","code":"HB025","lon":117.383,"lat":38.378,"name":"黄骅东","url":"","weather":"","val":0,"status":38.378,"val2":38.378,"type":1},{"gjzid":"54624","qy":"sn","glb":"20.750","code":"HB026","lon":117.332,"lat":38.447,"name":"羊三木","url":"","weather":"","val":0,"status":38.447,"val2":38.447,"type":1},{"gjzid":"54624","qy":"sn","glb":"31.500","code":"HB027","lon":117.297,"lat":38.584,"name":"窦庄子","url":"","weather":"","val":0,"status":38.584,"val2":38.584,"type":1},{"gjzid":"54622","qy":"sn","glb":"40.800","code":"HB028","lon":117.271,"lat":38.65,"name":"郭庄子","url":"","weather":"","val":0,"status":38.65,"val2":38.65,"type":1},{"gjzid":"54622","qy":"sn","glb":"51.100","code":"HB029","lon":117.25,"lat":38.689,"name":"北港农场","url":"","weather":"","val":0,"status":38.689,"val2":38.689,"type":1},{"gjzid":"54622","qy":"sn","glb":"60.450","code":"HB030","lon":117.252,"lat":38.749,"name":"大港水库","url":"","weather":"","val":0,"status":38.749,"val2":38.749,"type":1},{"gjzid":"123456","code":"654321","lon":117.385,"lat":38.833,"qy":"sn","glb":"70.0","name":"万家码头","url":"","weather":"","val":0,"status":38.749,"val2":38.749,"type":1},{"gjzid":"123456","code":"654321","lon":117.363,"lat":38.833,"qy":"sn","glb":"69.497","name":"黄万终点","url":"","weather":"","val":0,"status":38.749,"val2":38.749,"type":1},{"gjzid":"54517","qy":"sn","glb":"83.83","code":"HB031","lon":117.784,"lat":38.966,"name":"神港","url":"","weather":"","val":0,"status":38.811,"val2":38.811,"type":1}],"gridSetting":[{"post":0,"startPeriod":"000","endPeriod":"072","periodInterval":3,"fcstFrequency":12,"dlat":0.05,"dlon":0.05,"nlat":161,"nlon":161,"startLat":34.8,"endLat":42.8,"startLon":111.9,"endLon":119.9},{"post":1,"startPeriod":"072","endPeriod":"240","periodInterval":3,"fcstFrequency":12,"dlat":0.05,"dlon":0.05,"nlat":161,"nlon":161,"startLat":34.8,"endLat":42.8,"startLon":111.9,"endLon":119.9}]},"gridData":{},"objectData":{}}